Workbook

Sheet Read me
A1: Goods on Country — cost per bed, made simple
A2: v1 · 2026-06-02 · the numbers tie to the website cost model (/admin/cost-model)
B5: The one idea
B6: There are TWO different questions hiding inside "what does a bed cost?"
B7: 1. What does it cost to make ONE MORE bed? (the honest number — call it MARGINAL)
B8: 2. What does it cost to run the whole little operation, divided by how few beds we make this year?
B9: (this is where the scary "$1,900 a bed" comes from — it is just fixed costs ÷ too few beds)
B11: Lead with the marginal number. Treat the fixed running costs as a yearly block to fund, not a per-bed tax.
B13: How to use this workbook
B14: • Go to the ▶ Play tab. Change ONLY the yellow cells. Everything else recomputes.
B15: • The big green answers update live. The plain-English sentence at the bottom rewrites itself —
B16: that sentence is the thing you read aloud to a funder.
B17: • Parts / Fixed block / Easy-to-forget / Capital case are the detail behind the Play tab.
B19: The three numbers that matter
... B28: machine maintenance once in-house. ~$120K of mis-tagged Xero spend still inflates the raw "all-in" figure.

Sheet ▶ Play
A1: ▶ Play — change the yellow cells
A2: Yellow = your inputs · Grey = computed · Green = the answer
B4: YOUR INPUTS | E4: FIXED RUNNING COSTS (per year)
B5: Beds per year | C5: 100 | D5: try 100 / 500 / 1000 | E5: Founder production time | F5: =C10*C11
B6: Sell price per bed | C6: 600 | D6: $600 gift / $750 shop / $801 inst. | E6: Workshop rent (Goods share) | F6: ='Fixed block'!C6
B7: Plastic legs: BUY or MAKE | C7: BUY | D7: BUY=$344 Defy · MAKE=$70+labour | E7: Field travel to communities | F7: ='Fixed block'!C7
B8: Make-it labour /bed (if MAKE) | C8: 80 | D8: $80 factory · $130 community wage | E8: Admin / back-office | F8: ='Fixed block'!C8
B9: Long-haul freight /bed | C9: 150 | D9: $150@100/yr → $80@1000/yr | E9: =TOTAL fixed block / year | F9: =SUM(F5:F8)
B10: Founder PRODUCTION days/yr | C10: 30 | D10: of ~150 total — only these touch a bed | E10: Fixed cost spread per bed | F10: =F9/C5
B11: Founder day-rate | C11: 560 | D11: locked 2026-05-29
B13: WHAT ONE BED IS MADE OF | E13: THE ANSWERS
B14: Recycled-plastic legs | C14: =IF($C$7="BUY",344.05,70) | E14: Marginal cost — one more bed | F14: =C21
B15: Steel poles (×2) | C15: =Parts!C6 | E15: Fully-loaded cost / bed (reference only) | F15: =C21+F10
B16: Canvas | C16: =Parts!C7 | E16: Contribution / bed (price − marginal) | F16: =C6-C21
B17: Hardware (caps/screws/bolts) | C17: =Parts!C8 | E17: Breakeven (beds/yr to cover fixed block) | F17: =IF(C16>0,ROUND(F9/C16,0),"never at this price")
B18: Make-it labour | C18: =IF($C$7="BUY",65,$C$8) | E18: Annual surplus / (shortfall) | F18: =C16*C5-F9
B19: =DIRECT cost / bed | C19: =SUM(C14:C18)
B20: Read this aloud: | C20: =C9
B21: ="One more bed costs about $"&TEXT(C21,"#,##0")&" to make"&IF(C7="BUY"," (we buy the plastic legs)"," (we press our own plastic legs)")&". At $"&TEXT(C6,"#,##0")&"/bed we break even at "&IF(C16>0,TEXT(ROUND(F9/C16,0),"#,##0")&" beds a year","— we cannot break even at this price")&". At "&TEXT(C5,"#,##0")&" beds/yr we run a "&IF(C16*C5-F9>=0,"surplus","shortfall")&" of $"&TEXT(ABS(C16*C5-F9),"#,##0")&" a year"&IF(C16*C5-F9<0," — philanthropy bridges that gap.",".")
B25: Tip: set BUY + 100 beds + $600 to see today's reality; set MAKE + 500 beds + $750 to see the in-sourced target.

Sheet Scenarios
A1: Scenarios — the journey, side by side
A2: Each column is its own little model. Change the yellow cells in any column and compare.
C4: ① Today (buy kits) | D4: ② In-sourced @500 | E4: ③ Community @1,000 (fair wage)
B5: INPUTS (change me)
B6: Plastic legs: BUY / MAKE | C6: BUY | D6: MAKE | E6: MAKE
B7: Beds per year | C7: 100 | D7: 500 | E7: 1000
B8: Sell price per bed | C8: 600 | D8: 750 | E8: 750
B9: Make-it labour /bed (if MAKE) | C9: 80 | D9: 80 | E9: 130 | F9: $80 factory · $130 dignified community wage
B10: Long-haul freight /bed | C10: 150 | D10: 100 | E10: 80 | F10: falls as pallets fill at volume
B11: Founder PRODUCTION days/yr | C11: 30 | D11: 30 | E11: 30
B12: Founder day-rate | C12: 560 | D12: 560 | E12: 560
B13: Fixed block / year | C13: =C11*C12+27000+51000+14700 | D13: =D11*D12+27000+51000+14700 | E13: =E11*E12+27000+51000+14700
B14: RESULTS
B15: Direct cost / bed | C15: =IF(C6="BUY",344.05,70)+27+93.5+5.24+IF(C6="BUY",65,C9) | D15: =IF(D6="BUY",344.05,70)+27+93.5+5.24+IF(D6="BUY",65,D9) | E15: =IF(E6="BUY",344.05,70)+27+93.5+5.24+IF(E6="BUY",65,E9)
B16: Marginal cost / bed (one more bed) | C16: =C15+C10 | D16: =D15+D10 | E16: =E15+E10
B17: Fully-loaded / bed (reference only) | C17: =C16+C13/C7 | D17: =D16+D13/D7 | E17: =E16+E13/E7
B18: Contribution / bed (price − marginal) | C18: =C8-C16 | D18: =D8-D16 | E18: =E8-E16
B19: Breakeven (beds/yr) | C19: =IF(C18>0,ROUND(C13/C18,0),"never at this price") | D19: =IF(D18>0,ROUND(D13/D18,0),"never at this price") | E19: =IF(E18>0,ROUND(E13/E18,0),"never at this price")
B20: Annual surplus / (shortfall) | C20: =C18*C7-C13 | D20: =D18*D7-D13 | E20: =E18*E7-E13
B22: What each column says
C23: Buying kits at $600, we lose money on every bed — can't break even at any volume. | D23: Press our own legs + hit 500 beds at $750 → we run a real surplus. | E23: Even paying the full $130 community wage, scale makes it strongly profitable.

Sheet Parts
A1: Parts — the bill of materials
A2: Verified from invoices unless noted. Change C only with a new supplier quote.
B4: Line | C4: BUY $/bed | D4: MAKE $/bed | E4: Confidence | F4: Source
B5: Recycled-plastic legs (20kg HDPE) | C5: 344.05 | D5: 70 | E5: verified / modelled | F5: Defy INV-1602/1732 · MAKE=shred $55+diesel $15
B6: Galvanised steel poles (×2) | C6: 27 | D6: 27 | E6: verified | F6: DNA Steel, Notion BOM
B7: Canvas sleeping surface | C7: 93.5 | D7: 93.5 | E7: verified | F7: Centre Canvas, 3 invoices
B8: Hardware (4 caps, 16 screws, 2 bolts) | C8: 5.24 | D8: 5.24 | E8: verified/inferred | F8: Coastal Fasteners; bolt rate inferred
B9: Parts subtotal (materials only) | C9: =SUM(C5:C8) | D9: =SUM(D5:D8)
B11: First-principles raw floor: $128.99/bed. The gap to $469.79 is supply-chain markup — ~$289 of it the plastic kit alone (idiot index 8.6× vs $40 shred floor).

Sheet Fixed block
A1: Fixed block — running the business, per year
A2: These do NOT change per bed. The Play tab divides this by your chosen volume.
B4: Cost | C4: $/year | D4: Basis / to confirm
B5: Founder production time (links to Play C10×C11) | C5: ='▶ Play'!C10*'▶ Play'!C11 | D5: 30 of 150 days × $560 — FOUNDER-CONFIRM the split
B6: Workshop rent (Goods share, 50% of Kirmos) | C6: 27000 | D6: $4,500/mo verified; 50%-to-beds est — confirm w/ Nic
B7: Field travel to communities | C7: 51000 | D7: Largest line; anchored by $24,507 Utopia trip
B8: Admin / back-office | C8: 14700 | D8: v5/v6 figure, not yet itemised
B9: TOTAL fixed block / year | C9: =SUM(C5:C8)
B11: DELIBERATELY EXCLUDED: the other ~120 founder days (fundraising, commercial, governance) — they are how we raise capital and win orders, not a cost of building a bed. Putting them on the bed is what creates the fake "$840 of founder time per bed."

Sheet Easy-to-forget
A1: Easy-to-forget — reserves & fees we have NOT modelled
A2: Toggle these into the marginal cost to see the honest sensitivity. Most are placeholders until quoted.
B4: Cost | C4: Rate / amount | D4: $/bed (approx) | E4: Why it matters
B5: Warranty / replacement reserve | C5: 4% of parts | D5: =0.04*Parts!C9 | E5: 5-yr warranty to remote communities; no reserve carried today
B6: Payment processing (direct web sales) | C6: ~2% of price | D6: =0.02*'▶ Play'!C6 | E6: Stripe ~1.75%+$0.30; not on grant invoices
B7: Replacement freight (per warranty event) | C7: $150–300 event | D7: — | E7: A swap pays remote freight AGAIN — brutal logistics
B8: Insurance (liability/product) | C8: quote needed | D8: — | E8: Buried in whole-org $1.66M block; no Goods-only figure
B9: Accounting / external audit | C9: quote needed | D9: — | E9: Numbers currently unaudited; real if investors require reliance
B10: Machine maintenance/downtime (MAKE path) | C10: % of capex | D10: — | E10: In-house legs $150 ignore upkeep + capital recovery
B11: Community plastic collect/wash/sort | C11: $28–100/bed | D11: — | E11: 'Free' plastic still costs labour to make usable
B13: Modelled add to marginal (warranty + payment): | D13: =D5+D6
B14: Honest marginal WITH these in = Play marginal + the line above. The rest are real but un-quoted — show them as a list so no one forgets, even before we have firm numbers.

Sheet Capital case
A1: Capital case — why we ask for the plastic-processing kit
A2: The whole capex story in one screen: per-bed legs saving × volume vs the machine cost.
B4: INPUTS
B5: Gross capex (machines) | C5: 167000 | D5: band $112K–$222K
B6: Already invested | C6: 110046
B7: Saving per bed (buy $344 → make $150) | C7: 194.05
B8: Committed beds / year | C8: 500
B10: ANSWERS
B11: Net capital ask | C11: =C5-C6
B12: Annual saving from in-sourcing legs | C12: =C7*C8
B13: Payback (years on gross capex) | C13: =C5/(C7*C8)
B14: Volume reality check | C14: =IF(C8<300,"⚠ below 300/yr — capex not yet justified","✓ volume supports the capex")
B16: The line that matters: at ~500 beds/yr the kit pays for itself in under 2 years, then every bed keeps ~$194 of value (and the jobs) on-country instead of paying Defy's margin.
