Workbook

Sheet Assumptions
A1: GOC-only financial model, single input page (v1, 2026-07-21)
A2: Entity: the Goods on Country carve-out of A Curious Tractor Pty Ltd t/a Goods. YELLOW cells are the only inputs; every statement calculates from here. GST excluded. Labels: Verified = invoice/signed doc · Workpaper = our math, checkable · Modelled = from verified inputs, not demonstrated · Target = not signed.
A4: Input | B4: FY27 | C4: FY28 | D4: FY29 | E4: Label | F4: Source
A5: SALES
A6: Bed price ($/bed) | B6: 750 | C6: =B6 | D6: =B6 | E6: Verified | F6: canon.ts price list; one price everywhere
A7: Beds sold (units/yr) | B7: 200 | C7: 338 | D7: 500 | E7: Modelled | F7: ramp from verified ~120/yr run-rate (cost-story.ts:217) to ~338 break-even (engine) then growth toward ~1,000 capacity
A8: Share of beds pressed in-house (%) | B8: 0.5 | C8: 1 | D8: 1 | E8: Modelled | F8: capability proven: Maningrida Stretch run of 40 pressed at farm (Ben ruling 2026-07-21, INV-0303); rate ramps with equipment completion
A9: Washer revenue ($/yr) | B9: 0 | C9: 0 | D9: 0 | E9: Verified | F9: Pakkimjalki Kari is prototype, not for sale (CLAUDE.md products canon)
A10: UNIT COSTS
A11: Marginal cost per bed, buy-kit ($) | B11: 684.79 | C11: =B11 | D11: =B11 | E11: Verified (engine-locked) | F11: cost-story.ts:127 kit $344.05 + steel $27 + canvas $93.50 + hardware $5.24 + assembly $55.95 + freight ~$150
A12: Marginal cost per bed, pressed ($) | B12: 425.74 | C12: =B12 | D12: =B12 | E12: Modelled | F12: cost-story.ts:166; NOT yet measured at production rate; the funded measured run converts it
A13: FIXED BLOCK ($/yr)
A14: Facility (Kirmos share) | B14: 27000 | C14: =B14*(1+$B$19) | D14: =C14*(1+$B$19) | E14: Workpaper | F14: cost-story.ts:195 fixed block
A15: Founder production time (30d x $560) | B15: 16800 | C15: =B15*(1+$B$19) | D15: =C15*(1+$B$19) | E15: Workpaper | F15: engine.ts founder rate LOCKED $560/day
A16: Admin | B16: 14700 | C16: =B16*(1+$B$19) | D16: =C16*(1+$B$19) | E16: Workpaper | F16: cost-story.ts fixed block
A17: Field travel (relationship, fixed) | B17: 51000 | C17: =B17*(1+$B$19) | D17: =C17*(1+$B$19) | E17: Workpaper | F17: Ben ruling 2026-07-21: mostly fixed being-in-community time; delivery freight is in the per-bed line
A18: (sum check: block ≈ $109.5K/yr) | B18: =SUM(B14:B17) | C18: =SUM(C14:C17) | D18: =SUM(D14:D17) | E18: Workpaper | F18: cost-story.ts:195 ~$109,500
A19: Fixed cost annual growth (%) | B19: 0.03 | E19: Modelled | F19: placeholder CPI-ish; Ben/Matt to set
A20: EQUIPMENT
A21: Equipment already invested ($, opening PPE) | B21: 110046 | E21: Verified | F21: canon.ts:250; ~$80K TFN + ~$20K ACT
A22: New capex ($/yr) | B22: 60000 | C22: 20000 | D22: 0 | E22: Modelled | F22: within the $2-112K net remaining range (cost-story.ts:254); FY28 = contingency/moulds
A23: Depreciation rate (straight line, %/yr) | B23: 0.1 | E23: Modelled | F23: 10yr equipment life assumption; Matt to confirm policy
A24: Equipment maintenance (% of gross PPE/yr) | B24: 0.04 | E24: Modelled | F24: cost-story.ts:279 3-5% band, midpoint
A25: FUNDING (THE RAISE) — $0 SIGNED TODAY
A26: Grant income: Snow R4/R5 ($) | B26: 100000 | C26: 0 | D26: 0 | E26: Target | F26: 2026-07-03 stack; grant deed NOT signed
A27: Grant income: Centrecorp ($) | B27: 75000 | C27: 0 | D27: 0 | E27: Target | F27: 2026-07-03 stack; NOT signed
A28: Grant income: QBE Stage 2 match ($) | B28: 400000 | C28: 0 | D28: 0 | E28: Target | F28: up to $400K, requires >=1:1 SIGNED match by 31 Aug (04-qbe-pipeline.md); discretionary
A29: Other grants/philanthropy ($) | B29: 0 | C29: 50000 | D29: 0 | E29: Target | F29: placeholder for continuing philanthropy taper; taper design = gifts end at break-even
A30: SEFA loan drawn ($) | B30: 300000 | C30: 0 | D30: 0 | E30: Target | F30: repayable working-capital anchor, proposed, NOT signed
A31: SEFA interest rate (%/yr) | B31: 0.065 | E31: Modelled | F31: concessional indicative; term sheet TBC
A32: SEFA principal repayment ($/yr) | B32: 0 | C32: 100000 | D32: 100000 | E32: Modelled | F32: indicative 3yr amortisation from FY28; term sheet TBC
A33: WORKING CAPITAL
A34: Debtor days | B34: 60 | E34: Modelled | F34: B2B buyers pay slow (Rotary INV-0222 went 11 months overdue); 60d planning assumption
A35: Creditor days | B35: 30 | E35: Modelled | F35: supplier terms assumption
A36: Inventory days (of COGS) | B36: 30 | E36: Modelled | F36: materials bought ahead of builds
A37: OPENING POSITION (Ben/accountant to set)
A38: Opening cash ($) | B38: 50000 | E38: PLACEHOLDER | F38: set from bank; NOT a canon figure
A39: Opening receivables ($) | B39: 143000 | E39: Verified | F39: canon.ts:92 AR = Rotary $82.5K + Homeland $44K + Regional Arts $16.5K
A40: Tax rate on positive NPBT (%) | B40: 0.25 | E40: Modelled | F40: small business company rate; entity structure pre-Butterfly, Matt to confirm

Sheet P&L
A1: P&L — GOC carve-out (calculated; edit only the Assumptions page)
B3: FY27 | C3: FY28 | D3: FY29
A5: Bed revenue (beds x price) | B5: =Assumptions!B7*Assumptions!B6 | C5: =Assumptions!C7*Assumptions!B6 | D5: =Assumptions!D7*Assumptions!B6
A6: Blended marginal cost per bed | B6: =Assumptions!B8*Assumptions!B12+(1-Assumptions!B8)*Assumptions!B11 | C6: =Assumptions!C8*Assumptions!B12+(1-Assumptions!C8)*Assumptions!B11 | D6: =Assumptions!D8*Assumptions!B12+(1-Assumptions!D8)*Assumptions!B11
A7: COGS (beds x blended marginal) | B7: =-B7*Assumptions!B7 | C7: =-C7*Assumptions!C7 | D7: =-D7*Assumptions!D7
A8: Gross profit (contribution) | B8: =B5+B8 | C8: =C5+C8 | D8: =D5+D8
A10: Fixed block (facility, founder, admin, travel) | B10: =-Assumptions!B18 | C10: =-Assumptions!C18 | D10: =-Assumptions!D18
A11: Equipment maintenance | B11: =-Assumptions!B24*('Balance Sheet'!B10) | C11: =-Assumptions!B24*('Balance Sheet'!C10) | D11: =-Assumptions!B24*('Balance Sheet'!D10)
A12: EBITDA | B12: =B9+B11+B12 | C12: =C9+C11+C12 | D12: =D9+D11+D12
A13: Depreciation | B13: =-Assumptions!B23*'Balance Sheet'!B10 | C13: =-Assumptions!B23*'Balance Sheet'!C10 | D13: =-Assumptions!B23*'Balance Sheet'!D10
A14: EBIT | B14: =B13+B14 | C14: =C13+C14 | D14: =D13+D14
A15: Interest (SEFA) | B15: =-Assumptions!B31*'Balance Sheet'!B16 | C15: =-Assumptions!B31*'Balance Sheet'!C16 | D15: =-Assumptions!B31*'Balance Sheet'!D16
A16: Trading profit before grants and tax | B16: =B15+B16 | C16: =C15+C16 | D16: =D15+D16
A18: Grant income (Target: $0 signed today) | B18: =Assumptions!B26+Assumptions!B27+Assumptions!B28+Assumptions!B29 | C18: =Assumptions!C26+Assumptions!C27+Assumptions!C28+Assumptions!C29 | D18: =Assumptions!D26+Assumptions!D27+Assumptions!D28+Assumptions!D29
A19: Net profit before tax | B19: =B17+B19 | C19: =C17+C19 | D19: =D17+D19
A20: Tax (only if positive) | B20: =-MAX(B20,0)*Assumptions!B40 | C20: =-MAX(C20,0)*Assumptions!B40 | D20: =-MAX(D20,0)*Assumptions!B40
A21: NET PROFIT AFTER TAX | B21: =B20+B21 | C21: =C20+C21 | D21: =D20+D21
A24: Reference: FY26 actual Goods-only revenue $713,827 (accountant-signed carve-out, canon.ts:106; the ONLY external revenue figure) + $143,000 AR. FY26 included grant-funded delivery; this model separates trading from grants so the taper is visible.

Sheet Cash Flow
A1: Cash Flow — GOC carve-out (calculated; edit only the Assumptions page)
B3: FY27 | C3: FY28 | D3: FY29
A5: Net profit after tax | B5: ='P&L'!B22 | C5: ='P&L'!C22 | D5: ='P&L'!D22
A6: Add back depreciation | B6: =-'P&L'!B14 | C6: =-'P&L'!C14 | D6: =-'P&L'!D14
A7: (Increase) in receivables | B7: =-('Balance Sheet'!None7-Assumptions!B39) | C7: =-('Balance Sheet'!C7-'Balance Sheet'!B7) | D7: =-('Balance Sheet'!D7-'Balance Sheet'!C7)
A8: (Increase) in inventory | B8: =-('Balance Sheet'!B8-0) | C8: =-('Balance Sheet'!C8-'Balance Sheet'!B8) | D8: =-('Balance Sheet'!D8-'Balance Sheet'!C8)
A9: Increase in payables | B9: ='Balance Sheet'!B14-0 | C9: ='Balance Sheet'!C14-'Balance Sheet'!B14 | D9: ='Balance Sheet'!D14-'Balance Sheet'!C14
A10: Operating cash flow | B10: =SUM(B5:B9) | C10: =SUM(C5:C9) | D10: =SUM(D5:D9)
A12: Capex | B12: =-Assumptions!B22 | C12: =-Assumptions!C22 | D12: =-Assumptions!D22
A13: Investing cash flow | B13: =B12 | C13: =C12 | D13: =D12
A15: SEFA loan drawn | B15: =Assumptions!B30 | C15: =Assumptions!C30 | D15: =Assumptions!D30
A16: SEFA principal repaid | B16: =-Assumptions!B32 | C16: =-Assumptions!C32 | D16: =-Assumptions!D32
A17: Financing cash flow | B17: =B15+B16 | C17: =C15+C16 | D17: =D15+D16
A19: Net cash movement | B19: =B10+B13+B17 | C19: =C10+C13+C17 | D19: =D10+D13+D17
A20: Opening cash | B20: =Assumptions!B38 | C20: =B20 | D20: =C20
A21: CLOSING CASH | B21: =B19+B20 | C21: =C19+C20 | D21: =D19+D20

Sheet Balance Sheet
A1: Balance Sheet — GOC carve-out (calculated; edit only the Assumptions page)
B3: FY27 | C3: FY28 | D3: FY29
A5: ASSETS
A6: Cash | B6: ='Cash Flow'!B21 | C6: ='Cash Flow'!C21 | D6: ='Cash Flow'!D21
A7: Receivables (revenue x debtor days/365) | B7: ='P&L'!B5*Assumptions!B34/365 | C7: ='P&L'!C5*Assumptions!B34/365 | D7: ='P&L'!D5*Assumptions!B34/365
A8: Inventory (COGS x inventory days/365) | B8: =-'P&L'!B8*Assumptions!B36/365 | C8: =-'P&L'!C8*Assumptions!B36/365 | D8: =-'P&L'!D8*Assumptions!B36/365
A9: PPE at cost (opening + cumulative capex) | B9: =Assumptions!B21+Assumptions!B22 | C9: =B9+Assumptions!C22 | D9: =C9+Assumptions!D22
A10: PPE gross (avg base for dep/maint) | B10: =B9 | C10: =C9 | D10: =D9
A11: Accumulated depreciation | B11: =-'P&L'!B14*-1*0-'P&L'!B14*-1 | C11: =B11-'P&L'!C14 | D11: =C11-'P&L'!D14
A12: TOTAL ASSETS | B12: =B6+B7+B8+B9+B11 | C12: =C6+C7+C8+C9+C11 | D12: =D6+D7+D8+D9+D11
A14: Payables (COGS x creditor days/365) | B14: =-'P&L'!B8*Assumptions!B35/365 | C14: =-'P&L'!C8*Assumptions!B35/365 | D14: =-'P&L'!D8*Assumptions!B35/365
A16: SEFA loan balance | B16: =Assumptions!B30-Assumptions!B32 | C16: =B16+Assumptions!C30-Assumptions!C32 | D16: =C16+Assumptions!D30-Assumptions!D32
A17: TOTAL LIABILITIES | B17: =B14+B16 | C17: =C14+C16 | D17: =D14+D16
A19: EQUITY
A20: Opening funds employed (cash + AR + PPE) | B20: =Assumptions!B38+Assumptions!B39+Assumptions!B21 | C20: =B20 | D20: =C20
A21: Cumulative retained profit | B21: ='P&L'!B22 | C21: =B21+'P&L'!C22 | D21: =C21+'P&L'!D22
A22: TOTAL EQUITY | B22: =B20+B21 | C22: =C20+C21 | D22: =D20+D21
A24: CHECK (assets - liabilities - equity = 0) | B24: =B12-B17-B22 | C24: =C12-C17-C22 | D24: =D12-D17-D22
