Workbook
Name price: Inputs!$B$5
Name cost_plastic: Inputs!$B$6
Name cost_power: Inputs!$B$7
Name cost_consumables: Inputs!$B$8
Name cost_parts: Inputs!$B$9
Name cost_assembly: Inputs!$B$10
Name wage_per_bed: Inputs!$B$11
Name hours_per_bed: Inputs!$B$12
Name kg_in_bed: Inputs!$B$13
Name kg_pressed: Inputs!$B$14
Name freight_per_bed: Inputs!$B$15
Name plant_allowance: Inputs!$B$16
Name plants: Inputs!$B$17
Name running_cost: Inputs!$B$18
Name press_sheets_day: Inputs!$B$19
Name sheets_per_bed: Inputs!$B$20
Name days_per_week: Inputs!$B$21
Name weeks_per_year: Inputs!$B$22
Name assembly_ceiling: Inputs!$B$23
Name cnc_rate: Inputs!$B$24
Name bed_target: Inputs!$B$25
Name first_year_per_plant: Inputs!$B$26
Name tff_beds: Inputs!$B$27
Name bmd_beds: Inputs!$B$28
Name snow_beds: Inputs!$B$29
Name alive_beds: Inputs!$B$30
Name community_keeps: Inputs!$B$31
Name loan_amount: Inputs!$B$32
Name loan_service: Inputs!$B$33

Sheet Read me
A1: Goods on Country — the live model
A2: Built 10 September 2026 from Goods-financial-plan.xlsx, recalculated. Every figure traces to a cell there.
A4: How to use it | B4: Edit the yellow cells on Inputs. Nothing else. Every other tab is formulas and recalculates.
A5: What is different here | B5: Every input has a name. Formulas read the name, not the cell. Insert a row anywhere and nothing breaks. The 953KB master has 42,429 formulas and no names at all, which is why one inserted row changes its meaning.
A6: What wins when two disagree | B6: canon.ts and asset-canonical.ts for figures. DECISIONS.md for judgements. CONTEXT.md for language. This workbook for money.
A7: What is modelled, not measured | B7: The cost to make a bed, two hours of paid making, and 20 kg in a finished bed. The first fifty beds off each new plant replace all three with weighed and timed numbers.
A8: What is verified | B8: Beds sold and paid, the register count, the FY26 ledger, the funder invitations and their dates.
A9: What this does not hold | B9: The 6,100 rows of source provenance, the Xero extracts and the 36-month cash schedule. Those stay in the master.
A10: The one number that is zero | B10: Funding secured. Every other funding line is an invitation or a conversation.
A12: Tab | B12: What it answers
A13: Inputs | B13: Every driver, in one place. The only tab you edit.
A14: One bed | B14: What a bed is worth, what it costs, what stays, and how many carry the year.
A15: The plant | B15: What a plant costs, module by module, and against what benchmarks.
A16: Capacity | B16: How many beds a plant makes and which step sets the limit.
... A23: Claims | B23: Key figures with a grade and a source.

Sheet Inputs
A1: Inputs — the only cells you edit
A2: Yellow is yours. Each row has a name, and every other tab reads the name.
A4: Driver | B4: Value | C4: Unit | D4: Name used in formulas | E4: Where it comes from
A5: Bed price at the factory door | B5: 750 | C5: AUD | D5: price | E5: Model!B22. Ben's canon.
A6: Plastic in a bed's cost | B6: 60 | C6: AUD | D6: cost_plastic | E6: NM Play B58, own-sheets route.
A7: Electricity in a bed's cost | B7: 16.67 | C7: AUD | D7: cost_power | E7: NM Play B59.
A8: Consumables in a bed's cost | B8: 33.33 | C8: AUD | D8: cost_consumables | E8: NM Play B60.
A9: Bought parts in a bed's cost | B9: 125.74 | C9: AUD | D9: cost_parts | E9: NM Play B61. Poles 27, canvas 93.50, hardware 5.24.
A10: Assembly allowance | B10: 40 | C10: AUD | D10: cost_assembly | E10: NM Play B64. This is the line that makes 235.74 into 276.
A11: Paid making inside a bed | B11: 80 | C11: AUD | D11: wage_per_bed | E11: Two hours at the factory rate.
A12: Hours of paid making a bed | B12: 2 | C12: hours | D12: hours_per_bed | E12: Settled 10 Sep. The 6.5-hour figure is withdrawn.
A13: HDPE in a finished bed | B13: 20 | C13: kg | D13: kg_in_bed | E13: Design mass. NM Play B38.
A14: Shred pressed to make a bed | B14: 36 | C14: kg | D14: kg_pressed | E14: NM Play B21. Leg sheet 21, tab sheet 15.
A15: Freight a bed | B15: 100 | C15: AUD | D15: freight_per_bed | E15: Start!B49. Inherited estimate, routes need quotes.
A16: Allowance for one plant | B16: 150000 | C16: AUD | D16: plant_allowance | E16: Capital!C7. An allowance, not a quote.
... A33: Loan service a year | B33: 47522.88 | C33: AUD | D33: loan_service | E33: Cases!K6. 7% over five years.

Sheet One bed
A1: One bed
A2: Never cost-plus. The price carries the business, and the organisation is never divided by beds alone.
B4: AUD | C4: Note
A5: Price at the factory door | B5: =price | C5: What a funder pays for a community's first stock.
A6: Plastic | B6: =cost_plastic
A7: Electricity | B7: =cost_power
A8: Consumables | B8: =cost_consumables
A9: Bought parts | B9: =cost_parts | C9: Poles, canvas, hardware.
A10: Assembly allowance | B10: =cost_assembly | C10: The line that turns 235.74 into 276.
A11: Cost to make | B11: =cost_plastic+cost_power+cost_consumables+cost_parts+cost_assembly | C11: Modelled until the first fifty come off the line at working pace.
A12: Of which paid making | B12: =wage_per_bed | C12: Two hours. On country once a plant moves.
A13: Stays with Goods | B13: =price-(cost_plastic+cost_power+cost_consumables+cost_parts+cost_assembly) | C13: Carries Witta, the founders and the organisation.
A14: Freight | B14: =freight_per_bed | C14: On top, at cost, per community, paid by whoever buys the bed.
A16: Running the organisation a year | B16: =running_cost
A17: Beds a year that carry it, buyer pays freight | B17: =ROUNDUP(running_cost/(price-(cost_plastic+cost_power+cost_consumables+cost_parts+cost_assembly)),0) | C17: The break-even the deck prints.
A18: Beds a year that carry it, Goods pays freight | B18: =ROUNDUP(running_cost/(price-(cost_plastic+cost_power+cost_consumables+cost_parts+cost_assembly)-freight_per_bed),0) | C18: What carrying freight costs in beds.
A20: Kept in the community on sale | B20: =price*community_keeps | C20: Ben, 10 Sep: the community keeps the full sale price.

Sheet The plant
A1: The plant, module by module
A2: Thirteen modules and a site base. Four have a supplier price. Nine are estimates, and that is what the allowance margin is for.
A4: ID | B4: Module | C4: Low | D4: High | E4: Midpoint | F4: Price basis
A5: M01 | B5: 40ft shipping container | C5: 13000 | D5: 16000 | E5: 14500 | F5: Estimate or historical proxy
A6: M02 | B6: 20ft shipping container | C6: 6000 | D6: 10000 | E6: 8000 | F6: Estimate
A7: M03 | B7: Diesel generator, press-line sized | C7: 6600 | D7: 20000 | E7: 13300 | F7: Estimate. The widest range of any module
A8: M04 | B8: Crane placement and transport | C8: 1200 | D8: 2500 | E8: 1850 | F8: Quoted
A9: M05 | B9: Electrical fit-out, board, three-phase | C9: 3000 | D9: 8000 | E9: 5500 | F9: Estimate
A10: M06 | B10: Ventilation and fume extraction | C10: 1000 | D10: 3000 | E10: 2000 | F10: Estimate
A11: M07 | B11: Site prep, pad and levelling | C11: 500 | D11: 3000 | E11: 1750 | F11: Estimate. Site specific
A12: M08 | B12: PPE and startup consumables | C12: 500 | D12: 1500 | E12: 1000 | F12: Estimate
A13: M09 | B13: Collection and sorting | C13: 5000 | D13: 19500 | E13: 12250 | F13: Estimate
A14: M10 | B14: Shredding | C14: 19800 | D14: 19800 | E14: 19800 | F14: Telford Smith. A single price
A15: M11 | B15: Pressing, CNC and finishing | C15: 32780 | D15: 32780 | E15: 32780 | F15: Circularity bundle. A single price
A16: M12 | B16: Assembly and workshop | C16: 6387 | D16: 6387 | E16: 6387 | F16: Carbatec. A single price
A17: M13 | B17: Sales and delivery | C17: 0 | D17: 0 | E17: 0 | F17: Nothing priced here yet
B18: Every module and the site base | C18: =SUM(C5:C17) | D18: =SUM(D5:D17) | E18: =SUM(E5:E17)
B20: Against the benchmarks
B21: Replicate and install a site | C21: 113000 | F21: Capital!C31. The lean end.
B22: The allowance we ask for | C22: =plant_allowance | F22: Sits above the module high.
B23: Turnkey a site | C23: 207450 | F23: Capital!C32. Handed over running.
B24: The QBE request | C24: =plants*plant_allowance | F24: Two plants.

Sheet Capacity
A1: Capacity, and which step sets it
A2: The press is the jam. The router and the bench both have spare at every level of press output.
A4: Step | B4: Beds a day | C4: What it means
A5: Sort and shred | B5: =kg_pressed | C5: Kilograms of shred pressed for one bed, not a rate.
A6: Heat, press and cool | B6: =press_sheets_day/sheets_per_bed | C6: Six sheets a day, two sheets a bed. This sets the pace.
A7: CNC cut and finish | B7: =cnc_rate | C7: Spare capacity at every level of press output.
A8: Assemble, test and pack | B8: =assembly_ceiling | C8: An independent ceiling that staffing has to verify.
A10: The binding step | B10: =MIN(press_sheets_day/sheets_per_bed,cnc_rate,assembly_ceiling) | C10: Whichever is lowest is the plant's real rate.
A11: Beds a week | B11: =MIN(press_sheets_day/sheets_per_bed,cnc_rate,assembly_ceiling)*days_per_week
A12: Beds a year | B12: =MIN(press_sheets_day/sheets_per_bed,cnc_rate,assembly_ceiling)*days_per_week*weeks_per_year | C12: The ceiling on the same equipment.
A13: A plant's first year | B13: =first_year_per_plant | C13: The ramp we promise in Q6.
A14: Both plants, first year | B14: =first_year_per_plant*plants
A16: Days to make the target | B16: =ROUNDUP(bed_target/MIN(press_sheets_day/sheets_per_bed,cnc_rate,assembly_ceiling),0) | C16: Before downtime, at the binding rate.
A17: Shred needed for the target | B17: =bed_target*kg_pressed/1000 | C17: Tonnes through the press.

Sheet Impact
A1: The four impact areas
A2: Per bed, at one plant's first year and at the ceiling. Health is the reason the hardware exists and is never a claimed outcome.
A4: Area | B4: Unit | C4: Per bed | D4: At 200 beds | E4: At the ceiling | F4: Where the claim stops
A5: Recycling | B5: kg pressed | C5: =kg_pressed | D5: =kg_pressed*first_year_per_plant | E5: =kg_pressed*'Capacity'!B12 | F5: Design mass is not measured diversion. Weigh feedstock, accepted parts, offcuts and waste per batch.
A6: Recycling | B6: kg in the beds | C6: =kg_in_bed | D6: =kg_in_bed*first_year_per_plant | E6: =kg_in_bed*'Capacity'!B12 | F6: The difference between the two rows is offcut or loss until yield is measured.
A7: Health | B7: people off the floor | C7: 1 | D7: =first_year_per_plant | E7: ='Capacity'!B12 | F7: Scabies and rheumatic heart disease are why the hardware exists. No clinical outcome is claimed.
A8: Employment | B8: hours of paid making | C8: =hours_per_bed | D8: =hours_per_bed*first_year_per_plant | E8: =hours_per_bed*'Capacity'!B12 | F8: Report actual paid hours and payments. The legacy 4.8 hours a bed is comparison only.
A9: Employment | B9: AUD of wage | C9: =wage_per_bed | D9: =wage_per_bed*first_year_per_plant | E9: =wage_per_bed*'Capacity'!B12 | F9: Inside the cost to make, not on top of it.
A10: Community enterprise | B10: AUD kept on sale | C10: =price*community_keeps | D10: =price*community_keeps*first_year_per_plant | E10: =price*community_keeps*'Capacity'!B12 | F10: Only if the community sells the bed. Ownership is a pathway until rights and transfers are evidenced.

Sheet Asks
A1: Every funder line
A2: Secured is zero. An invitation is not an award and a conversation is not an invitation.
A4: Funder | B4: Type | C4: Amount | D4: Beds it buys | E4: Stage | F4: Condition and next evidence
A5: QBE Foundation | B5: Grant | C5: =plants*plant_allowance | E5: Application | F5: Closes 25 Sep noon. Outcome 23 Oct. Pre-conditions 13 Nov. Builds plants, buys no beds.
A6: Tim Fairfax Family Foundation | B6: Grant | C6: 100000 | D6: =tff_beds | E6: Invitation | F6: $300,000 over three years. Operating support, unrestricted. Due 9 Oct. Board late November.
A7: Brian M. Davis Charitable Foundation | B7: Grant | C7: 100000 | D7: =bmd_beds | E7: Invitation | F7: Due 25 Sep. Board 19 Nov. Pays only once all project funding is confirmed, per the budget template B16.
A8: Snow Foundation | B8: Grant | C8: 100000 | D8: =snow_beds | E8: To ask | F8: Ben, 10 Sep: an ask shaped like Brian M. Davis, counted as bed money. Snow was 57% of last year's receipts.
A9: ALIVE, University of Melbourne | B9: Paid | C9: 75000 | D9: =alive_beds | E9: Received | F9: Already paid. Outside the target. The reckoning records more received than these beds.
A10: Sefa Backing the Bold | B10: Loan | C10: =loan_amount | E10: Discussion | F10: No EOI sent. Our number, not Sefa's. 7% over five years.
A11: Oonchiumpa, DEWR | B11: Grant | C11: 150000 | E11: Offer letter | F11: Alice Springs plant only, pass-through. Outside every scenario.
A12: NIAA via Oonchiumpa | B12: Grant | C12: 150000 | E12: Discussion | F12: Alice Springs plant only, pass-through. Outside every scenario.
A13: Dusseldorp | B13: Grant | C13: 0 | E13: Discussion | F13: No Goods ask in email. The $15,000 in June was CONTAINED.
A14: Paul Ramsay and Atlassian | B14: Loan | C14: 0 | E14: Discussion | F14: Announced 7 Sep. No approach made.
A15: Minderoo | B15: Grant | C15: 0 | E15: Closed | F15: Paused 14 May. Not a current prospect.
A17: Secured today | C17: 0 | F17: No signed commitment with a satisfied condition.
A18: Beds funded against the target | C18: =tff_beds+bmd_beds+snow_beds | F18: If every invited ask lands.
A19: Beds still to find | C19: =MAX(0,bed_target-(tff_beds+bmd_beds+snow_beds))
A20: Bed money still to find | C20: =MAX(0,bed_target-(tff_beds+bmd_beds+snow_beds))*price

Sheet Cases
A1: Five cases
A2: Read straight out of the master. Receipts are hypothetical and none of them is secured.
A4: Case | B4: QBE | C4: Loan | D4: Beds | E4: Priced spend | F4: Receipts | G4: Peak cash need | H4: Interpretation
A5: Full | B5: 300000 | C5: 200000 | D5: 400 | E5: 763084.33 | F5: 700000 | G5: 110607.21 | H5: Capacity-constrained initial stock. Cases!A6.
A6: Smaller, one plant | B6: 150000 | C6: 100000 | D6: 400 | E6: 613084.33 | F6: 450000 | G6: 186845.77 | H6: Stages capital, keeps the stock target. Peak need is higher than Full.
A7: No QBE | B7: 0 | C7: 200000 | D7: 400 | E7: 763084.33 | F7: 400000 | G7: 410607.21 | H7: A stress test, not permission to spend unfunded money.
A8: Receipts three months late | B8: 300000 | C8: 200000 | D8: 400 | E8: 763084.33 | F8: 700000 | G8: 479488.63 | H8: Same money, later. Peak need more than quadruples.
A9: Half the Goods sales | B9: 300000 | C9: 200000 | D9: 400 | E9: 763084.33 | F9: 700000 | G9: 110607.21 | H9: Direct Goods sales are already zero, so halving them changes nothing.

Sheet Responsibilities
A1: Who pays for what
A2: Goods funds initial stock, delivery and agreed initial support, plus the plant capital. Community organisations fund local operations and keep their sales.
A4: Line | B4: Goods | C4: Community | D4: Combined | E4: Boundary
A5: Plant capital | B5: 300000 | C5: 0 | D5: 300000 | E5: The QBE request. Asset title and transfer to agree.
A6: Making and freight | B6: 125534.33 | C6: 0 | D6: 125534.33 | E6: Capacity-constrained forecast.
A7: Facility fixed costs | B7: 35350 | C7: 420700 | D7: 456050 | E7: Community facility wages, rent and training sit in the community operating plan.
A8: Youth support | B8: 40000 | C8: 0 | D8: 40000 | E8: Four communities at $10,000 facilitation each. None named yet.
A9: Shared network | B9: 262200 | C9: 0 | D9: 262200 | E9: Includes a known cost-overlap question.
A10: Priced spending | B10: 763084.33 | C10: 420700 | D10: 1183784.3 | E10: Goods overheads are not automatically the incremental raise.

Sheet The year
A1: The annual roll-up
A2: Year one of the selected case. Negative forecast cash is an unfunded gap, never an approved overdraft.
A4: Line | B4: Year 1 | C4: Year 2 | D4: Year 3 | E4: Basis
A5: Grant income | B5: 500000 | C5: 100000 | D5: 100000 | E5: Statements!B8. Includes possible grants.
A6: Goods invoiced | B6: 0 | C6: 0 | D6: 0 | E6: Direct Goods sales are zero in the current case.
A7: Making expense | B7: 91549.33 | C7: 118072.5 | D7: 118072.5
A8: Freight | B8: 40000 | C8: 50000 | D8: 50000
A9: Network costs | B9: 262200 | C9: 262200 | D9: 262200
A10: Facility costs | B10: 35350 | C10: 35350 | D10: 35350
A11: Youth support | B11: 40000 | C11: 0 | D11: 0
A12: Depreciation | B12: 30000 | C12: 30000 | D12: 30000
A13: Loan interest | B13: 12903.28 | C13: 10400.63 | D13: 7717.06
A14: Profit before tax | B14: -12002.62 | C14: -406023.13 | D14: -403339.56 | E14: Includes possible grant income. Not a trading surplus.
A15: Net cash movement | B15: -110607.21 | C15: -412942.88 | D15: -412942.88
A16: Planned beds within capacity | B16: 400 | C16: 1220 | D16: 1220 | E16: Statements!B68.

Sheet Sites
A1: The sites
A2: Witta exists. The two new plants are working choices and neither community has agreed to a build.
A4: ID | B4: Site | C4: Route | D4: Year 1 | E4: Year 2 | F4: Year 3 | G4: Note
A5: WITTA | B5: Goods production facility at The Harvest | C5: Own sheets | D5: 400 | E5: 500 | F5: 500 | G5: Existing. Initial community trading stock is made here.
A6: NEW1 | B6: Palm Island, working choice | C6: Own sheets | D6: 0 | E6: 500 | F6: 500 | G6: Council, community and PICC have each asked. First beds about three months after funding.
A7: NEW2 | B7: Maningrida, working choice | C7: Own sheets | D7: 0 | E7: 500 | F7: 500 | G7: 40 beds already built with us, pressed at Witta and assembled at Gamardi.
A8: ALICE | B8: Alice Springs, through Oonchiumpa | C8: Own sheets | D8: 0 | E8: 0 | F8: 0 | G8: Funded by DEWR and NIAA. Outside this raise.

Sheet Claims
A1: Key figures, graded
A2: Verified means the source was read. Modelled means calculated. Conflict means two sources disagree and a person must rule.
A4: Claim | B4: Figure | C4: Grade | D4: Source
A5: The QBE request | B5: $300,000 | C5: Verified | D5: QBE!D14 and A54, Funding F01. Ben, 9 Sep 2026.
A6: Funding secured to date | B6: $0 | C6: Verified | D6: Funding!F19.
A7: A bed at the factory door | B7: $750 | C7: Verified | D7: Model!B22.
A8: Cost to make a bed | B8: $276 | C8: Modelled | D8: 235.74 on the annual-staff basis plus the $40 assembly allowance.
A9: Stays with Goods | B9: $474 | C9: Verified | D9: Model!B24, derived.
A10: Running the organisation | B10: $297,550 | C10: Verified | D10: Model!B25.
A11: Break-even on beds alone | B11: 628 beds | C11: Modelled | D11: Model!B26, buyer pays freight. 796 if Goods carries it.
A12: The press sets the pace | B12: 3 beds a day | C12: Verified | D12: NM Play B46. CNC does 8.56 and assembly 5.
A13: Shred pressed for one bed | B13: 36 kg | C13: Verified | D13: NM Play B21. Leg sheet 21, tab sheet 15.
A14: HDPE in a finished bed | B14: 20 kg | C14: Modelled | D14: Design mass. NM Play B38. Definition conflict remains against D06's 40 kg.
A15: Beds sold and paid, all time | B15: 320, $343,481 | C15: Verified | D15: Ten invoices.
... A29: Capacity against the target | B29: 360 or 400 | C29: Conflict | D29: D17 says capacity is 360. Start!B7 says 400 supported.
