Workbook

Sheet Control Panel
A1: Goods on Country — Financial Model · CONTROL PANEL
A2: ONE place to play. Change a yellow dial below and every tab recomputes via formulas. Method dial (B6) selects which marginal cost feeds COGS via CHOOSE(). Built for QBE advisory (Matt) + investor review. Verified figures = live Xero mirror 2026-05-29; founder time, scale & scenarios are MODELLED. v0.2-locked anchors matched exactly.
A4: DIALS — yellow cells are the inputs you turn
A5: Dial | B5: Value | C5: Unit | D5: Note | E5: Status
A6: Volume — beds per year | B6: 500 | C6: beds/yr | D6: Forward annual production volume. Drives COGS, revenue, breakeven absorption, factory payback. | E6: MODELLED
A7: Manufacturing method (1-4) | B7: 1 | C7: 1=Kit 2=Panels 3=Factory 4=Community | D7: CHOOSE driver. 1 Buy-Kit (today, no capex) · 2 Buy-Panels (avoid) · 3 Factory in-house · 4 Community. Selects marginal cost from Unit Cost tab. | E7: MODELLED
A8: # containerised factories | B8: 0 | C8: units | D8: Each containerised plant unlocks in-house legs (method 3/4). Adds capex; cuts per-bed cost. 0 = buy Defy kits. | E8: MODELLED / TARGET
A9: Founder day-rate | B9: 560 | C9: AUD/day | D9: LOCKED 2026-05-29 (Ben). $560/day = $140,000/yr at 250 days (Day-3 fair-market). Drives founder cost + fixed block. | E9: LOCKED
A10: Founder days/yr (total) | B10: 150 | C10: days/yr | D10: LOCKED. 150 days x $560 = $84,000/yr founder cost. Split 30 prod / 50 fund / 25 comm / 45 gov. | E10: LOCKED
A11: Founder production-days/yr | B11: 30 | C11: days/yr | D11: LOCKED. ONLY these 30 days touch unit cost = $16,800/yr in the bed fixed block. Other 120 days = cost-of-capital, not unit cost. | E11: LOCKED
A12: Opening cash @ 1 May 2026 | B12: 50000 | C12: AUD | D12: WORKING figure, pending the ACT-accounts carve-out (NAB Visa ACT + ACT Everyday attributable to Goods). Re-bases the entire cashflow trough. | E12: WORKING
A13: Retail / institutional price per bed | B13: 750 | C13: AUD | D13: VERIFIED — shop stretch-bed-single. Unified website price (2026-05-26). | E13: VERIFIED
A14: Long-haul freight per bed | B14: 150 | C14: AUD/bed | D14: Variable, per-bed (corrected from overhead in v6). Remote delivery to community. | E14: MODELLED
A16: HEADLINE OUTPUTS — live formulas off the dials (do not type here)
A17: Output | B17: Value | C17: Unit | D17: How it is computed | E17: Status
A18: Selected marginal cost per bed | B18: =CHOOSE($B$7,'Unit Cost'!$F$25,'Unit Cost'!$F$26,'Unit Cost'!$F$27,'Unit Cost'!$F$28) | C18: AUD/bed | D18: CHOOSE(method, Kit/Panels/Factory/Community marginal totals from Unit Cost tab). THIS feeds COGS. | E18: MODELLED
A19: Selected direct cost per bed (materials+conversion) | B19: =CHOOSE($B$7,'Unit Cost'!$E$25,'Unit Cost'!$E$26,'Unit Cost'!$E$27,'Unit Cost'!$E$28) | C19: AUD/bed | D19: CHOOSE(method) on the direct-cost column (excludes long-haul freight). | E19: MODELLED
A20: Gross margin per bed (price − marginal) | B20: =$B$13-$B$18 | C20: AUD/bed | D20: Price dial minus selected marginal cost. | E20: MODELLED
A21: Gross margin % | B21: =($B$13-$B$18)/$B$13 | C21: % | D21: (price − marginal) / price. | E21: MODELLED
A22: Annual fixed block | B22: =$B$23 | C22: AUD/yr | D22: Kirmos facility + founder production share + admin + field travel (from Wages & People + Unit Cost). | E22: MODELLED
A23: Annual fixed block (value) | B23: ='Wages & People'!$B$8+'Unit Cost'!$B$56 | C23: AUD/yr | D23: Founder production cost ($560x30) + non-founder fixed block ($92,700 = Kirmos $27K + admin $14.7K + field $51K). | E23: MODELLED
A24: Breakeven volume (beds/yr) | B24: =IF(($B$13-$B$18)<=0,"n/a",ROUND($B$22/($B$13-$B$18),0)) | C24: beds/yr | D24: Annual fixed block / gross margin per bed. (Defy-kit path contribution is thin → very high breakeven.) | E24: MODELLED
A25: Revenue at selected volume | B25: =$B$6*$B$13 | C25: AUD/yr | D25: Volume x price (forward, projected). | E25: MODELLED
A26: COGS at selected volume | B26: =$B$6*$B$18 | C26: AUD/yr | D26: Volume x selected marginal cost. | E26: MODELLED
A27: Operating surplus BEFORE founder time (annual fwd) | B27: =$B$6*($B$13-$B$18)-'Unit Cost'!$B$56-'Wages & People'!$E$17 | C27: AUD/yr | D27: Gross profit − non-founder fixed block ($92,700) − future-hire wages (toggle-driven). Excludes ALL founder time. | E27: MODELLED
A28: Operating surplus AFTER founder time (annual fwd) | B28: =$B$27-$B$9*$B$10 | C28: AUD/yr | D28: Surplus before founder time minus full founder cost ($560 x 150 = $84,000). | E28: MODELLED
A29: Cash trough (36-mo, off opening-cash dial) | B29: ='Cashflow (36mo)'!$B$9 | C29: AUD | D29: Minimum cumulative cash across 36 months — recomputes live off the opening-cash dial. | E29: MODELLED
A30: Runway at trough (months, modelled burn) | B30: ='Cashflow (36mo)'!$B$10 | C30: months | D30: Months of runway at the cash trough on the modelled monthly burn. | E30: MODELLED
A32: VERIFIED ACTUALS (period, cash basis — not forward): Revenue received $649,710.79 · AR owed $82,500 (Rotary) · Goods cash out $309,126 · Operating surplus before founder time $340,585 · after period founder time ~$151,585. See P&L tab. Forward outputs above are MODELLED off the dials.
A34: ENTITY: A Curious Tractor Pty Ltd (ABN 36 697 347 676) t/a Goods on Country; DGR pathway via The Butterfly Movement Ltd. AP ≈ $0 owed; NO director loan. Revenue ~89% grant-funded (not trading profit). Capex treated in cash. Not audited — management workpaper.

Sheet Unit Cost
A1: Unit Cost — BOM, 4 build methods, Idiot Index, Containerisation
A2: Direct cost per bed by method. Control Panel method dial (B7) selects which marginal total (col F) feeds COGS via CHOOSE. All BOM rates VERIFIED from invoices (Defy INV-1602/1732, DNA Steel Notion BOM, Centre Canvas 3 invoices, Coastal Fasteners). 20kg HDPE/bed.
A4: CANONICAL BOM (Defy-kit path direct materials = $469.79/bed)
A5: Component | B5: Qty | C5: Unit cost | D5: Line cost | E5: Supplier | F5: Source / confidence
A6: HDPE plastic kit (legs, cut & finished) | B6: 1 | C6: 344.05 | D6: =B6*C6 | E6: Defy Design | F6: Defy INV-1602 + INV-1732 — VERIFIED
A7: Galvanised steel poles (gal pipe) | B7: 1 | C7: 27 | D7: =B7*C7 | E7: DNA Steel Direct | F7: Notion BOM StretchBed v2 — VERIFIED
A8: Canvas sleeping surface | B8: 1 | C8: 93.5 | D8: =B8*C8 | E8: Centre Canvas | F8: 3 invoices 2026, 270 covers — VERIFIED
A9: Round ribbed end caps (27mm) | B9: 4 | C9: 0.8 | D9: =B9*C9 | E9: Hardware supplier | F9: 4 x $0.80 — VERIFIED
A10: Frame screws | B10: 16 | C10: 0.065 | D10: =B10*C10 | E10: Coastal Fasteners | F10: RB20247673190 — VERIFIED
A11: Frame bolts | B11: 2 | C11: 0.5 | D11: =B11*C11 | E11: Coastal Fasteners | F11: 2 x $0.50 est — INFERRED
A12: Defy-kit direct materials total | D12: =SUM(D6:D11)
A14: FOUR BUILD METHODS — direct $/bed + marginal (incl. long-haul freight from Control Panel)
A15: Method | B15: Plastic legs/bed | C15: Other materials | D15: Conversion (diesel+labour+assembly+local freight) | E15: Direct total | F15: Marginal total (+ long-haul) | G15: Status / verdict
A25: 1 · Buy-Kit (today, no capex) | B25: =C6 | C25: =(D7+D8+D9+D10+D11) | D25: =40+25 | E25: =B25+C25+D25 | F25: =E25+'Control Panel'!$B$14 | G25: Best bought-in path today. MODELLED (verified inputs)
A26: 2 · Buy-Panels (avoid) | B26: 400 | C26: =(D7+D8+D9+D10+D11) | D26: =5+53.33 | E26: =B26+C26+D26 | F26: =E26+'Control Panel'!$B$14 | G26: Worst value — paying press margin. VERIFIED inputs
A27: 3 · Factory in-house | B27: =55+15+80 | C27: =(D7+D8+D9+D10+D11) | D27: 0 | E27: =B27+C27+D27 | F27: =E27+'Control Panel'!$B$14 | G27: TARGET. Needs press+CNC capex. MODELLED
A28: 4 · Community (free feedstock + volunteer) | B28: 15 | C28: =(D7+D8+D9+D10+D11) | D28: 0 | E28: =B28+C28+D28 | F28: =E28+'Control Panel'!$B$14 | G28: Vision. Council feedstock + CDP labour (future). FUTURE
A30: SELECTED method (from Control Panel dial) | B30: ='Control Panel'!$B$7 | D30: Selected marginal $/bed → | E30: =CHOOSE('Control Panel'!$B$7,F25,F26,F27,F28)
A32: IDIOT INDEX (current paid ÷ raw-material floor)
A33: Element | B33: Raw floor | C33: Current paid | D33: Idiot index | E33: Biggest lever? | F33: Note
A34: HDPE kit (Defy cut+finished) | B34: 40 | C34: 344.05 | D34: =ROUND(C34/B34,1) | E34: YES — headline | F34: In-source shred+press+CNC → ~$150/bed; moves ~$194/bed + captures ~$289 Defy margin
A35: HDPE pre-pressed panel (alt) | B35: 40 | C35: 400 | D35: =ROUND(C35/B35,1) | E35: avoid | F35: Pay press margin but still CNC+assemble — worst value
A36: Canvas (Centre Canvas) | B36: 38.5 | C36: 93.5 | D36: =ROUND(C36/B36,1) | E36: no | F36: In-house sewing only at volume
A37: Steel poles (DNA Steel) | B37: 12.67 | C37: 27 | D37: =ROUND(C37/B37,1) | E37: no | F37: Reasonable; NT-procurement premium worth keeping
A38: End caps | B38: 2.6 | C38: 3.2 | D38: =ROUND(C38/B38,1) | E38: no | F38: Near cost
A39: Screws | B39: 1.04 | C39: 1.04 | D39: =ROUND(C39/B39,1) | E39: no | F39: Already raw rate
A40: Bolts | B40: 0.6 | C40: 1 | D40: =ROUND(C40/B40,1) | E40: no | F40: Trivial $ impact
A41: Defy assembly labour | B41: 60 | C41: 55.95 | D41: =ROUND(C41/B41,1) | E41: no | F41: Competitive; in-sourcing is a jobs/mission move
A43: CONTAINERISATION (per containerised factory)
A44: Item | B44: Value | C44: Unit | D44: Source / note
A45: Capex per factory — low | B45: 112000 | C45: AUD | D45: shredder $15-30K + press $80-150K + CNC $15-40K + tools $2K (v6)
A46: Capex per factory — high | B46: 222000 | C46: AUD | D46: high end of equipment band (firm quotes pending)
A47: Already invested (facility + Carbatec tooling) | B47: 110046 | C47: AUD | D47: sits inside the $323,106 cash spend — VERIFIED
A48: Net capital ask — low | B48: =B45-B47 | C48: AUD | D48: capex low − already invested
A49: Net capital ask — high | B49: =B46-B47 | C49: AUD | D49: capex high − already invested
A50: Per-bed saving buy-kit → in-house legs | B50: =B25-B27 | C50: AUD/bed | D50: Buy-kit legs $344.05 − factory legs $150 = ~$194; up to $259 vs full kit path
A51: Annual saving at selected volume | B51: ='Control Panel'!$B$6*B50 | C51: AUD/yr | D51: volume x per-bed leg saving
A52: Payback (years) on net-low capex at selected volume | B52: =IF(B51=0,"n/a",ROUND(B48/B51,1)) | C52: years | D52: net-low capex / annual saving
A55: NON-FOUNDER ANNUAL FIXED BLOCK (Kirmos + admin + field travel)
A56: Non-founder fixed block ($27,000 + $14,700 + $51,000) | B56: =27000+14700+51000 | C56: AUD/yr | D56: Kirmos facility 50% of $4,500/mo + admin + lumpy field travel. Founder production share added separately (Wages tab).

Sheet Wages & People
A1: Wages & People — founder time, FTE sensitivity, future hires
A2: Founder cost driven by Control Panel dials (day-rate $560 x days). Production share goes to the bed fixed block; the rest is cost-of-capital + customer-acquisition (NOT unit cost). FTE sensitivity per the advisor's $140,000/yr fair-market ask. Future hires are toggle-driven.
A4: FOUNDER COST (LOCKED 2026-05-29)
A5: Line | B5: Value | C5: Unit | D5: Source / treatment
A6: Founder cost per year (day-rate x total days) | B6: ='Control Panel'!$B$9*'Control Panel'!$B$10 | D6: $560 x 150 = $84,000/yr. LOCKED.
A7: of which production share (30 days) — in bed fixed block | B7: ='Control Panel'!$B$9*'Control Panel'!$B$11 | D7: $560 x 30 = $16,800/yr. ONLY part touching unit cost.
A8: Founder production cost (fixed-block input) | B8: ='Control Panel'!$B$9*'Control Panel'!$B$11 | D8: Referenced by Control Panel + Unit Cost fixed block.
A9: fundraising/commercialisation/governance (120 days) — NOT unit cost | B9: ='Control Panel'!$B$9*('Control Panel'!$B$10-'Control Panel'!$B$11) | D9: $560 x 120 = $67,200/yr. Cost-of-capital + customer-acq + ACT-wide.
A11: FUTURE HIRES (toggle 1=on / 0=off in col B; cost flows to P&L opex)
A12: Role | B12: On (1/0) | C12: Annual cost | D12: Start month | E12: Effective annual cost (on x cost)
A13: General Manager / Head of Manufacturing | B13: 0 | C13: 120000 | D13: Mth 7 | E13: =B13*C13
A14: Sales / BD #1 | B14: 0 | C14: 90000 | D14: Mth 7 | E14: =B14*C14
A15: Sales / BD #2 | B15: 0 | C15: 90000 | D15: Mth 13 | E15: =B15*C15
A16: Sales / BD #3 | B16: 0 | C16: 90000 | D16: Mth 19 | E16: =B16*C16
A17: TOTAL future-hire annual cost (toggled-on) | E17: =SUM(E13:E16)
A19: FTE SENSITIVITY — combined founder FTE on $140,000/yr fair-market basis (advisor ask)
A20: Scenario | B20: Ben FTE | C20: Nic FTE | D20: Combined FTE | E20: Annual founder cost
A21: Conservative | B21: 0.25 | C21: 0.25 | D21: 0.5 | E21: =140000*D21
A22: Mid | B22: 0.5 | C22: 0.5 | D22: 1 | E22: =140000*D22
A23: High | B23: 0.75 | C23: 0.5 | D23: 1.25 | E23: =140000*D23
A24: All-in | B24: 0.8 | C24: 0.7 | D24: 1.5 | E24: =140000*D24
A26: FTE sensitivity uses the $140,000/yr fair-market basis (= $560/day x 250 days). The LOCKED headline uses 150 days x $560 = $84,000/yr. Both reconcile at the $560/day rate. This table is the advisor's combined-FTE view; the locked figure is the working basis.

Sheet Revenue
A1: Revenue — verified actuals base + forward projection
A2: ACTUALS VERIFIED off the live Xero mirror 2026-05-29. FORWARD = Control Panel Volume x Price, split by segment. Revenue to date is ~89% donor-funded institutional — this is NOT trading profit.
A4: VERIFIED ACTUALS (period, cash basis)
A5: Metric | B5: Value | C5: Status | D5: Source
A6: Revenue billed (ACCREC) | B6: 732210.79 | C6: VERIFIED | D6: Live Xero mirror; project_code=ACT-GD
A7: Revenue received (16 PAID invoices) | B7: 649710.79 | C7: VERIFIED | D7: matched RECEIVE txns
A8: Accounts receivable owed (Rotary INV-0222) | B8: 82500 | C8: VERIFIED | D8: no matching RECEIVE txn — genuinely owed
A9: Grant revenue (cumulative) | B9: 611462 | C9: VERIFIED | D9: income_type=grant
A10: Commercial revenue (cumulative) | B10: 73449 | C10: VERIFIED | D10: income_type=commercial
A12: REVENUE MIX BY SEGMENT (to date — Day 5 basis on $684,911)
A13: Segment | B13: To date | C13: % of total | D13: Status | E13: Forward note
A14: Donor-funded institutional distribution | B14: 611461 | C14: 0.893 | D14: VERIFIED | E14: Centrecorp/Snow-type grant-funded placements
A15: Direct institutional commercial | B15: 45499 | C15: 0.066 | D15: VERIFIED | E15: Bulk B2B sale at $750
A16: Corporate sponsorship / RAP | B16: 12000 | C16: 0.018 | D16: VERIFIED | E16: RAP-funded bed sponsorship
A17: Community / maker partners | B17: 15950 | C17: 0.023 | D17: VERIFIED | E17: Community-led orders
A18: Government procurement | B18: 0 | C18: 0 | D18: TO CONFIRM | E18: Needs Supply Nation cert
A19: Direct retail / B2C | B19: 0 | C19: 0 | D19: TO CONFIRM | E19: Needs standing inventory
A20: Adjacent markets | B20: 0 | C20: 0 | D20: TO CONFIRM | E20: Future product lines
A21: Total revenue to date | B21: =SUM(B14:B20)
A22: FLAG: $94,500 of ACT-GD revenue is currently UNTAGGED grant-vs-commercial — segment split provisional until tagged (accountant item).
A24: FORWARD PROJECTION (Volume x Price — MODELLED)
A25: Segment | B25: Share of fwd volume | C25: Beds | D25: Price | E25: Forward revenue
A26: Donor-funded institutional | B26: 0.6 | C26: =ROUND('Control Panel'!$B$6*B26,0) | D26: ='Control Panel'!$B$13 | E26: =C26*D26
A27: Direct institutional commercial | B27: 0.2 | C27: =ROUND('Control Panel'!$B$6*B27,0) | D27: ='Control Panel'!$B$13 | E27: =C27*D27
A28: Corporate / RAP | B28: 0.08 | C28: =ROUND('Control Panel'!$B$6*B28,0) | D28: ='Control Panel'!$B$13 | E28: =C28*D28
A29: Community / maker | B29: 0.07 | C29: =ROUND('Control Panel'!$B$6*B29,0) | D29: ='Control Panel'!$B$13 | E29: =C29*D29
A30: Direct retail / B2C | B30: 0.05 | C30: =ROUND('Control Panel'!$B$6*B30,0) | D30: ='Control Panel'!$B$13 | E30: =C30*D30
A31: TOTAL forward revenue (= Volume x Price) | B31: Shares should sum to 100% | E31: =SUM(E26:E30)

Sheet P&L
A1: P&L — verified actuals reconciliation + forward (dial-driven)
A2: ACTUALS reconcile to the locked v0.2: surplus before founder time $340,585; after period founder time ~$151,585. FORWARD P&L is dial-driven (Revenue − COGS − wages/overhead − founder time).
A4: VERIFIED ACTUALS — PERIOD (single cash basis)
A5: Line | B5: Amount | C5: Status | D5: Source
A6: Revenue received | B6: 649710.79 | C6: VERIFIED | D6: live Xero mirror, 16 PAID invoices
A7: Total ACT-GD bank spend (NAB Visa ACT + ACT Everyday) | B7: 323106 | C7: VERIFIED | D7: single cash basis
A8: Less: 1300 Washer reclass to ACT-FM | B8: -13980 | C8: VERIFIED | D8: washing machine belongs ACT-FM
A9: Goods cash out (bank spend − washer reclass) | B9: =B7+B8
A10: Operating surplus BEFORE founder time | B10: =B6-$B$9 | C10: VERIFIED basis | D10: reconciles to ~$340,585
A11: Operating margin before founder time (on received) | B11: =$B$10/B6 | C11: MODELLED
A12: Founder time over the period ($560 x 150 x 27/12) | B12: ='Control Panel'!$B$9*'Control Panel'!$B$10*27/12 | C12: MODELLED | D12: 27-month cash-actuals span
A13: Operating surplus AFTER founder time (period) | B13: =$B$10-$B$12 | C13: VERIFIED − MODELLED | D13: reconciles to ~$151,585
A15: FORWARD ANNUAL P&L (dial-driven)
A16: Line | B16: Amount | C16: Status | D16: How computed
A17: Revenue (Volume x Price) | B17: ='Control Panel'!$B$6*'Control Panel'!$B$13 | C17: MODELLED | D17: Volume x Price dials
A18: COGS (Volume x selected marginal cost) | B18: =-'Control Panel'!$B$6*CHOOSE('Control Panel'!$B$7,'Unit Cost'!$F$25,'Unit Cost'!$F$26,'Unit Cost'!$F$27,'Unit Cost'!$F$28) | C18: MODELLED | D18: CHOOSE on method dial
A19: Gross profit | B19: =B17+B18
A20: Non-founder fixed block (Kirmos + admin + field) | B20: =-'Unit Cost'!$B$56 | C20: MODELLED
A21: Future-hire wages (toggle-driven) | B21: =-'Wages & People'!$E$17 | C21: MODELLED
A22: Operating surplus BEFORE founder time (fwd) | B22: =B19+B20+B21
A23: Founder time ($560 x 150) | B23: =-'Control Panel'!$B$9*'Control Panel'!$B$10 | C23: LOCKED
A24: Operating surplus AFTER founder time (fwd) | B24: =B22+B23
A26: Forward P&L is illustrative annual run-rate at the dialled volume/method. COGS uses the selected marginal cost; fixed block + founder time are annual. Change the method dial on the Control Panel and Gross profit + both surplus lines move.

Sheet Balance Sheet & WC
A1: Balance Sheet & Working Capital — scaffold
A2: AP genuinely owed ≈ $0 (AUTHORISED bills = payment-matching gap, paid from ACT accounts). NO director loan ($0 personal spend). Net WC = +$82,500 (Rotary AR). Capex = containerised factories. This is a scaffold, not a balanced sheet — accountant items flagged TO CONFIRM.
A4: ASSETS
A5: Line item | B5: Amount | C5: Status | D5: Source / note
A6: Cash — opening @ 1 May 2026 | B6: ='Control Panel'!$B$12 | C6: WORKING | D6: LIVE DIAL. $50,000 placeholder = ACT-accounts carve-out attributable to Goods.
A7: Accounts receivable — Rotary INV-0222 | B7: 82500 | C7: VERIFIED | D7: ACT-GD ACCREC genuinely owed; no matching RECEIVE txn.
A8: Accounts receivable — full ageing | B8: — | C8: TO CONFIRM | D8: 30/60/90 ageing from accountant.
A9: Inventory — finished beds + WIP | B9: — | C9: TO CONFIRM | D9: Not yet valued. Day 6 modelled $50K one-time build.
A10: Plant & equipment — capex invested | B10: 110046 | C10: VERIFIED | D10: Carbatec tooling $10,046 + facility; inside the $323,106 cash spend.
A11: Plant & equipment — containerised factories (planned) | B11: ='Control Panel'!$B$8*'Unit Cost'!$B$45 | C11: TARGET | D11: # factories dial x gross capex per factory (low $112K). Capex band $112K-$222K; net ask $90K-$200K after $110K invested.
A12: R&D Tax Incentive refund receivable | B12: — | C12: TO CONFIRM | D12: ~$80K/yr modelled; accrual treatment TBC.
A14: LIABILITIES
A15: Line item | B15: Amount | C15: Status | D15: Source / note
A16: Accounts payable — genuinely owed | B16: 0 | C16: VERIFIED | D16: ≈ $0. The ~$124,878 AUTHORISED bills = payment-matching gap, NOT debt.
A17: AUTHORISED ACCPAY bills (matching gap — memo only) | B17: 124878 | C17: VERIFIED | D17: Already paid from ACT accounts; apply existing payments, do not pay again.
A18: GST net payable (rough, accountant to finalise) | B18: 29657 | C18: MODELLED | D18: output GST $62,019 − input GST $32,362.
A19: Director loan / reimbursement | B19: 0 | C19: VERIFIED | D19: NONE. All ACT-GD spend from ACT business accounts; $0 personal.
A20: Debt — SEFA working capital (planned, not drawn) | B20: 300000 | C20: MODELLED | D20: Day 8 concessional ~4-6%, close target Nov 2026.
A22: WORKING-CAPITAL SIGNAL (verified basis — NOT a squeeze)
A23: Receivables due (AR) | B23: 82500
A24: Payables genuinely owed (AP) | B24: 0
A25: Net working-capital signal (AR − AP) | B25: =B23-B24 | D25: Net POSITIVE ≈ +$82,500. v0.1's −$44.4K 'squeeze' was an artefact. NO working-capital squeeze.

Sheet Cashflow (36mo)
A1: Cashflow — 36 months (May 2026 → Apr 2029)
A2: MODELLED. Opening cash = LIVE DIAL (Control Panel). Cumulative column is FORMULA-DRIVEN off the dial — the trough recomputes live. Capital injections are TOGGLES (col D, 1=on/0=off). Base-case monthly deltas from Day 6. No working-capital squeeze (AP ≈ $0).
A4: CAPITAL INJECTIONS (toggle col B, 1=on/0=off — MODELLED, not committed)
A5: Injection | B5: On (1/0) | C5: Amount | D5: Month | E5: Applied
A6: QBE Catalysing Impact match | B6: 1 | C6: 400000 | D6: Sep 2026 | E6: =B6*C6
A7: SEFA working-capital loan | B7: 1 | C7: 300000 | D7: Nov 2026 | E7: =B7*C7
A8: Anchor philanthropic raise | B8: 1 | C8: 500000 | D8: Jan 2027 | E8: =B8*C8
A9: Cash trough (minimum cumulative cash) | B9: =MIN(E14:E49) | D9: Recomputes live off the opening-cash dial. Base ($50K opening) ~ -$94K Aug-26.
A10: Runway at trough (months, modelled burn) | B10: =IF(MIN(E14:E49)>=0,"positive throughout",ROUND(MIN(E14:E49)/ABS(AVERAGE(B15:B22)),1)) | D10: Trough cash / avg monthly op burn (negative phase). Illustrative.
A12: MONTHLY CASHFLOW (cumulative recomputes off opening-cash dial)
A13: Month | B13: Net op cashflow | C13: Capital in | D13: Net monthly Δ | E13: Cumulative cash | F13: Buffer state
A14: May 2026 | B14: 0 | C14: 0 | D14: =B14+C14 | E14: ='Control Panel'!$B$12+D14 | F14: =IF(E14<0,"NEGATIVE",IF(E14<140000,"BELOW_FLOOR",IF(E14<280000,"BELOW_TARGET","OK")))
A15: Jun 2026 | B15: -48161 | C15: 0 | D15: =B15+C15 | E15: =E14+D15 | F15: =IF(E15<0,"NEGATIVE",IF(E15<140000,"BELOW_FLOOR",IF(E15<280000,"BELOW_TARGET","OK")))
A16: Jul 2026 | B16: -48161 | C16: 0 | D16: =B16+C16 | E16: =E15+D16 | F16: =IF(E16<0,"NEGATIVE",IF(E16<140000,"BELOW_FLOOR",IF(E16<280000,"BELOW_TARGET","OK")))
A17: Aug 2026 | B17: -48161 | C17: 0 | D17: =B17+C17 | E17: =E16+D17 | F17: =IF(E17<0,"NEGATIVE",IF(E17<140000,"BELOW_FLOOR",IF(E17<280000,"BELOW_TARGET","OK")))
A18: Sep 2026 | B18: -2042 | C18: =$E$6 | D18: =B18+C18 | E18: =E17+D18 | F18: =IF(E18<0,"NEGATIVE",IF(E18<140000,"BELOW_FLOOR",IF(E18<280000,"BELOW_TARGET","OK")))
A19: Oct 2026 | B19: -54208 | C19: 0 | D19: =B19+C19 | E19: =E18+D19 | F19: =IF(E19<0,"NEGATIVE",IF(E19<140000,"BELOW_FLOOR",IF(E19<280000,"BELOW_TARGET","OK")))
A20: Nov 2026 | B20: -54208 | C20: =$E$7 | D20: =B20+C20 | E20: =E19+D20 | F20: =IF(E20<0,"NEGATIVE",IF(E20<140000,"BELOW_FLOOR",IF(E20<280000,"BELOW_TARGET","OK")))
A21: Dec 2026 | B21: -12875 | C21: 0 | D21: =B21+C21 | E21: =E20+D21 | F21: =IF(E21<0,"NEGATIVE",IF(E21<140000,"BELOW_FLOOR",IF(E21<280000,"BELOW_TARGET","OK")))
A22: Jan 2027 | B22: -12875 | C22: =$E$8 | D22: =B22+C22 | E22: =E21+D22 | F22: =IF(E22<0,"NEGATIVE",IF(E22<140000,"BELOW_FLOOR",IF(E22<280000,"BELOW_TARGET","OK")))
A23: Feb 2027 | B23: 7681 | C23: 0 | D23: =B23+C23 | E23: =E22+D23 | F23: =IF(E23<0,"NEGATIVE",IF(E23<140000,"BELOW_FLOOR",IF(E23<280000,"BELOW_TARGET","OK")))
A24: Mar 2027 | B24: 7681 | C24: 0 | D24: =B24+C24 | E24: =E23+D24 | F24: =IF(E24<0,"NEGATIVE",IF(E24<140000,"BELOW_FLOOR",IF(E24<280000,"BELOW_TARGET","OK")))
A25: Apr 2027 | B25: 7681 | C25: 0 | D25: =B25+C25 | E25: =E24+D25 | F25: =IF(E25<0,"NEGATIVE",IF(E25<140000,"BELOW_FLOOR",IF(E25<280000,"BELOW_TARGET","OK")))
A26: May 2027 | B26: 97281 | C26: 0 | D26: =B26+C26 | E26: =E25+D26 | F26: =IF(E26<0,"NEGATIVE",IF(E26<140000,"BELOW_FLOOR",IF(E26<280000,"BELOW_TARGET","OK")))
A27: Jun 2027 | B27: 40000 | C27: 0 | D27: =B27+C27 | E27: =E26+D27 | F27: =IF(E27<0,"NEGATIVE",IF(E27<140000,"BELOW_FLOOR",IF(E27<280000,"BELOW_TARGET","OK")))
A28: Jul 2027 | B28: 40000 | C28: 0 | D28: =B28+C28 | E28: =E27+D28 | F28: =IF(E28<0,"NEGATIVE",IF(E28<140000,"BELOW_FLOOR",IF(E28<280000,"BELOW_TARGET","OK")))
A29: Aug 2027 | B29: 40000 | C29: 0 | D29: =B29+C29 | E29: =E28+D29 | F29: =IF(E29<0,"NEGATIVE",IF(E29<140000,"BELOW_FLOOR",IF(E29<280000,"BELOW_TARGET","OK")))
A30: Sep 2027 | B30: 40000 | C30: 0 | D30: =B30+C30 | E30: =E29+D30 | F30: =IF(E30<0,"NEGATIVE",IF(E30<140000,"BELOW_FLOOR",IF(E30<280000,"BELOW_TARGET","OK")))
A31: Oct 2027 | B31: 40000 | C31: 0 | D31: =B31+C31 | E31: =E30+D31 | F31: =IF(E31<0,"NEGATIVE",IF(E31<140000,"BELOW_FLOOR",IF(E31<280000,"BELOW_TARGET","OK")))
A32: Nov 2027 | B32: 40000 | C32: 0 | D32: =B32+C32 | E32: =E31+D32 | F32: =IF(E32<0,"NEGATIVE",IF(E32<140000,"BELOW_FLOOR",IF(E32<280000,"BELOW_TARGET","OK")))
A33: Dec 2027 | B33: 40000 | C33: 0 | D33: =B33+C33 | E33: =E32+D33 | F33: =IF(E33<0,"NEGATIVE",IF(E33<140000,"BELOW_FLOOR",IF(E33<280000,"BELOW_TARGET","OK")))
A34: Jan 2028 | B34: 40000 | C34: 0 | D34: =B34+C34 | E34: =E33+D34 | F34: =IF(E34<0,"NEGATIVE",IF(E34<140000,"BELOW_FLOOR",IF(E34<280000,"BELOW_TARGET","OK")))
... A49: Apr 2029 | B49: 60000 | C49: 0 | D49: =B49+C49 | E49: =E48+D49 | F49: =IF(E49<0,"NEGATIVE",IF(E49<140000,"BELOW_FLOOR",IF(E49<280000,"BELOW_TARGET","OK")))
A51: OPENING-CASH SENSITIVITY (illustrates how the dial moves the trough)
A52: Opening cash | B52: Trough cash | C52: Trough month | D52: Read
A53: 30000 | B53: −$171K (downside basis) | C53: Nov 2026 | D53: Tight — needs earlier capital
A54: 50000 | B54: −$94K (base) | C54: Aug 2026 | D54: Bridged by Sep QBE + Nov SEFA
A55: 100000 | B55: −$15K (upside) | C55: Aug 2026 | D55: Comfortable bridge

Sheet Scenarios
A1: Scenarios — Base / Upside / Downside + investment block
A2: MODELLED (Day 9). The cash trough appears in all three — depth varies with opening carve-out + capital timing. Investment block (bottom) is the simple lever set Matt extends: deploy N factories + hire team → effect on cost/capex/cash.
A4: BASE / UPSIDE / DOWNSIDE
A5: Metric | B5: Downside | C5: Base | D5: Upside | E5: Status
A6: Opening cash (ACT-accounts carve-out) | B6: 30000 | C6: 50000 | D6: 100000 | E6: MODELLED
A7: Cash first negative | B7: May 2026 | C7: Jun 2026 | D7: Aug 2026 | E7: MODELLED
A8: Trough (worst cash) | B8: -171000 | C8: -94000 | D8: -15000 | E8: MODELLED
A9: Trough month | B9: Nov 2026 | C9: Aug 2026 | D9: Aug 2026 | E9: MODELLED
A10: Capital injections total | B10: 650000 | C10: 1200000 | D10: 3540000 | E10: MODELLED
A11: Year 1 (FY27) revenue | B11: 690000 | C11: 1130000 | D11: 1580000 | E11: MODELLED
A12: Year 1 close cash | B12: 0 | C12: 992000 | D12: 2200000 | E12: MODELLED
A13: Year 3 close cash (36mo) | B13: 867000 | C13: 3327100 | D13: 7960000 | E13: MODELLED
A14: Probability of scenario | B14: 0.3 | C14: 0.3 | D14: 0.125 | E14: MODELLED
A16: INVESTMENT-SCENARIO BLOCK (for Matt to extend — driven off Control Panel dials)
A17: Lever | B17: Value | C17: Effect
A18: Containerised factories deployed (Control Panel dial) | B18: ='Control Panel'!$B$8 | C18: Each unlocks in-house legs (method 3/4)
A19: Capex deployed (factories x net-low) | B19: ='Control Panel'!$B$8*'Unit Cost'!$B$45 | C19: Cash out / balance sheet capex
A20: Per-bed cost reduction (kit → factory legs) | B20: ='Unit Cost'!$B$25-'Unit Cost'!$B$27 | C20: ~$194/bed leg saving
A21: Annual cost saving at selected volume | B21: ='Control Panel'!$B$6*('Unit Cost'!$B$25-'Unit Cost'!$B$27) | C21: Volume x per-bed saving
A22: Future hires toggled-on cost | B22: ='Wages & People'!$E$17 | C22: GM/BD capacity (Wages tab toggles)
A23: Selected marginal cost (method dial) | B23: =CHOOSE('Control Panel'!$B$7,'Unit Cost'!$F$25,'Unit Cost'!$F$26,'Unit Cost'!$F$27,'Unit Cost'!$F$28) | C23: Feeds COGS

Sheet Use of Funds
A1: Use of Funds — capital ask allocation
A2: Maps the QBE / capital ask to deployment. QBE is match-contingent: Goods must raise ~$400K to unlock the $400K match. Figures MODELLED; edit the Amount column to re-allocate.
A4: ALLOCATION
A5: Use | B5: Amount | C5: % of ask | D5: Note
A6: Inventory & materials (standing stock) | B6: 250000 | C6: =B6/$B$12 | D6: Bulk HDPE/steel/canvas + finished-bed buffer for B2C
A7: Containerised plant deployment (capex) | B7: 200000 | C7: =B7/$B$12 | D7: 1-2 containerised factories; net of $110K already invested
A8: Working capital | B8: 150000 | C8: =B8/$B$12 | D8: Bridge the structural May→Sep cash trough
A9: GM / BD / finance capacity | B9: 200000 | C9: =B9/$B$12 | D9: GM/Head of Manufacturing + 1-2 Sales/BD hires (Wages toggles)
A10: Impact & reporting (MEL) | B10: 80000 | C10: =B10/$B$12 | D10: SIH V4 + QBE inclusion/climate MEL framework
A11: Contingency | B11: 120000 | C11: =B11/$B$12 | D11: ~12% buffer on the raise
A12: TOTAL capital ask | B12: =SUM(B6:B11) | C12: =SUM(C6:C11)
A14: QBE match logic: the $400K match is an OUTPUT of raising ~$400K first (SEFA + anchor philanthropy). Capex line reconciles to the v6 net capital ask ($90K-$200K after $110K invested).

Sheet Assumptions & Provenance
A1: Assumptions & Provenance
A2: Goods-only financial model, best-available data 2026-05-29. Verified figures from the live Xero mirror; founder time, scale and scenarios are modelled. Built for QBE advisory (Matt) + investor review. Entity: A Curious Tractor Pty Ltd (ABN 36 697 347 676) t/a Goods on Country; DGR pathway via The Butterfly Movement Ltd.
A4: PROVENANCE KEY
A5: Label | B5: Meaning
A6: VERIFIED | B6: Queried directly from a named source (live Xero mirror rows, supplier invoices, shop price).
A7: MODELLED | B7: Forecast or assumption (founder-time scenarios, 36-mo cashflow, unit cost at scale, capital timing).
A8: TARGET | B8: Future operating intent (factory cost, containerised plant).
A9: TO CONFIRM | B9: Gap — row scaffolded, value NOT fabricated. Must close before the model is 'closed'.
A11: EVERY INPUT — value, source, confidence
A12: Input | B12: Value | C12: Confidence | D12: Source
A13: Volume (default) | B13: 500 beds/yr | C13: MODELLED | D13: planning default; dial
A14: Manufacturing method (default) | B14: 1 = Buy-Kit | C14: MODELLED | D14: today's path, no capex
A15: # containerised factories (default) | B15: 0 | C15: MODELLED / TARGET | D15: dial; capex band $112K-$222K
A16: Founder day-rate | B16: $560/day | C16: LOCKED (verified basis) | D16: Ben 2026-05-29; $140K/yr at 250 days
A17: Founder days/yr | B17: 150 | C17: LOCKED | D17: Ben 2026-05-29; 30/50/25/45 split
A18: Founder production-days/yr | B18: 30 | C18: LOCKED | D18: Ben 2026-05-29; only these touch unit cost
A19: Opening cash @ 1 May 2026 | B19: $50,000 | C19: WORKING | D19: pending ACT-accounts carve-out
A20: Retail/institutional price | B20: $750 | C20: VERIFIED | D20: shop stretch-bed-single
A21: Long-haul freight/bed | B21: $150 | C21: MODELLED | D21: variable; corrected from overhead (v6)
A22: HDPE kit (Defy) | B22: $344.05/bed | C22: VERIFIED | D22: Defy INV-1602 + INV-1732
A23: Steel poles | B23: $27.00/bed | C23: VERIFIED | D23: DNA Steel Notion BOM
... A50: Cash trough (base, $50K opening) | B50: −$94,000 | C50: MODELLED | D50: Aug 2026; Day 6/9
A52: NON-NEGOTIABLE ALIGNMENT (do not reintroduce retracted framings)
A53: • AP ≈ $0 owed; NO director loan; NO 'overdue payables / working-capital squeeze'. The ~$124,878 AUTHORISED bills are a payment-matching gap.
A54: • Expenses on a SINGLE CASH BASIS: $323,106 bank spend, less $13,980 washer reclass = $309,126 Goods cash out.
A55: • Founder rate $560/day LOCKED. Entity: A Curious Tractor Pty Ltd (ABN 36 697 347 676) t/a Goods on Country; DGR via The Butterfly Movement Ltd.
A56: • Revenue ~89% grant-funded = NOT trading profit. Capex treated in cash. Model is a management workpaper — NOT audited; accountant sign-off pending.
